src/control/control_unit.v
module control_unit(input wire	      clk,
		    input wire	      rst,
		    input wire [7:0]  mem_data_in,
		    input wire [7:0]  r0_stat,
		    input wire	      flag_stat,
		    output reg [7:0]  mem_data_out,
		    output reg [15:0] adress_line,
		    output reg	      mem_sel,
		    output reg	      mem_read,
		    output reg [2:0]  r1,
		    output reg [2:0]  r2,
		    output reg [2:0]  r3,
		    output reg [3:0]  alu_out,
		    output reg	      f_ch,
		    output reg	      r_ch,
		    output reg	      rb_sel,
		    output reg	      imme_sel,
		    output reg [7:0]  imme_out
		    );
   
   
   


   // first implement instruction fetch

   reg [3:0] state;
   reg [3:0] if_state;
   reg [3:0] load_state;


   reg [15:0] pc;
   wire [15:0] pc1;
   wire [15:0] pc2;
   wire [15:0] pc3;
   wire [15:0] pc4;
   

   reg [3:0]   alu_state;
   

   reg [2:0]   r1_s;
   reg [2:0]   r2_s;
   reg [2:0]   r3_s;
   reg [3:0]   alu_out_s;
   // reg	       f_ch_s;
   // reg	       r_ch_s;
   reg	       imme;
   reg	       jmp;
   reg	       sto;
   reg [7:0]   imme_high;
   reg [7:0]   imme_low;
   
   
   assign pc1 = pc + 1;
   assign pc2 = pc + 2;
   assign pc3 = pc + 3;
   assign pc4 = pc + 4;



   
   

   always @(posedge clk) begin


      if (rst) begin
	 state        <= 4'h0;
	 if_state     <= 4'h0;
	 load_state   <= 4'h0;
	 alu_state    <= 4'h0;
	 pc           <= 16'h0000;

	 r1_s         <= 3'b000;
	 r2_s         <= 3'b000;
	 r3_s         <= 3'b000;
	 alu_out_s    <= 4'h0;
	 // f_ch_s       <= 1'b0;
	 // r_ch_s       <= 1'b0;
	 imme         <= 1'b0;
	 jmp          <= 1'b0;
	 sto          <= 1'b0;
	 imme_high    <= 8'h00;
	 imme_low     <= 8'h00;

	 // Outputs
	 r1           <= 3'b000;
	 r2           <= 3'b000;
	 r3           <= 3'b000;
	 alu_out      <= 4'h0;
	 f_ch         <= 1'b0;
	 r_ch         <= 1'b0;
	 rb_sel       <= 1'b0;
	 imme_sel     <= 1'b0;
	 imme_out     <= 8'h00;
	 mem_sel      <= 1'b0;
	 mem_read     <= 1'b0;        // disabled by default after reset
	 mem_data_out <= 8'h00;
	 adress_line  <= 16'h0000;
      end else begin

	 r1         <= r1_s;          // keep latched values from fetch
	 r2         <= r2_s;
	 r3         <= r3_s;
	 alu_out    <= alu_out_s;

	 r_ch       <= 1'b0;
	 f_ch       <= 1'b0;
	 rb_sel     <= 1'b0;

	 imme_sel   <= imme;
	 imme_out   <= imme_high;

	 mem_sel    <= 1'b0;
	 mem_read   <= 1'b1;
	 mem_data_out <= 8'h00;
	 adress_line <= 16'h0000;
	 
	 case (state)
	   default: begin
	      state <= 4'h0;
	   end
	   
	   4'h0: begin
	      case (if_state) 
		4'h0: begin
		   adress_line <= pc;
		   mem_sel <= 1;
		   mem_read <= 1;
		   if_state <= 4'h1;
		end
		

		4'h1: begin
		   adress_line <= pc1;
		   mem_sel <= 1;
		   mem_read <= 1;

		   alu_out_s <= mem_data_in[7:4];
		   imme <= mem_data_in[3];
		   r1_s <= mem_data_in[2:0];
		   if_state <= 4'h2;
		   
		end // case: 4'h01

		4'h2: begin


		   jmp <= mem_data_in[7];
		   r2_s <= mem_data_in[6:4];
		   sto <= mem_data_in[3];
		   r1_s <= mem_data_in[2:0];

		   if (imme) begin
		      adress_line <= pc2;
		      mem_sel <= 1;
		      mem_read <= 1;
		      if_state <= 4'h3;
		   end else begin
		      mem_sel <= 0;
		      if_state <= 4'h5;
		   end
		   
		end // case: 4'h2
		
		
		4'h3: begin
		   adress_line <= pc3;
		   mem_sel <= 1;
		   mem_read <= 1;


		   imme_high <= mem_data_in;
		   
		   if_state <= 4'h4;
		end // case: 4'h3
		
		4'h4: begin
		   imme_low <= mem_data_in;
		   mem_sel <= 0; // stop selecting memory now
		   if_state <= 4'h5;
		end // case: 4'h4

		4'h5: begin
		   // instruction fetched now goto decode
		   pc <= pc4;
		   if_state <= 4'h0;
		   state <= 4'h1;
		end
		
		default: if_state <= 4'h0;
	      endcase; // case (if_state)
	   end // case: 4'h0
	   
	   4'h1: begin
	      // now I decode here, look at h5 state of if_state
	      // things will be latched after decoding

	      // immediately latch in the immediate operand so that 1 mux can select 1 register or immediate to ALU


	      // Defaults
	      // Register selects – keep the values latched from fetch
	      r1         <= r1_s;
	      r2         <= r2_s;
	      r3         <= r3_s;
	      alu_out    <= alu_out_s;

	      // Writeback control – default disabled
	      r_ch       <= 1'b0;
	      f_ch       <= 1'b0;
	      rb_sel     <= 1'b0;      // 0 = no register write


	      imme_sel   <= imme;      // pass through the immediate flag
	      imme_out   <= imme_high; // send the high byte of immediate (or zero)

	      // Memory control – default disabled
	      mem_sel    <= 1'b0;
	      mem_read   <= 1'b0;
	      mem_data_out <= 8'h00;
	      adress_line <= 16'h0000;

	      if (jmp) begin

		 // there are ALU instructions to set the flag stat
		 // the programmer will run that instruction, set the flag
		 // and jump
		 // there are 'less than' and 'equal to' and 'always set flag' instructions in alu
		 if (flag_stat) begin
		    pc <= {imme_high, imme_low};
		    state <= 4'h0;
		 end else begin
		    pc <= pc;
		    state <= 4'h0;
		 end
	      end else begin
		 // check if sto is set
		 // sto is high -> either load or store
		 // ALU not needed, so the 4 bits will be used to
		 // select load or store
		 if (sto) begin
		    // this is going to be complex, so gonna write later
		    // immediate must always be high here
		    // or not, just let assembler do it's job.
		    // doesn't matter anyway
		    
		    case (alu_out_s)
		      4'h0: begin
			 state <= 4'h2; // store
		      end

		      default: begin
			 state <= 4'h3; // load
		      end
		      
		    endcase; // case (alu_out_s)
		    
		    
		 end else begin


		    case (alu_state)
		      default: begin
			 alu_state <= 4'h0;
		      end
		      4'h0: begin
			 //start by sending from the register bank to alu
			 rb_sel <= 1;
			 r1 <= r1_s;
			 r2 <= r2_s;
			 r3 <= r3_s;
			 alu_out <= alu_out_s;
			 f_ch <= 0;
			 r_ch <= 0;
			 alu_state <= 4'h1;
		      end // case: begin...

		      4'h1: begin
			 // wait for a clock cycle for alu to settle down
			 alu_state <= 4'h2;
		      end

		      4'h2: begin
			 rb_sel <= 1;
			 f_ch <= 1;
			 r_ch <= 1;
			 alu_state <= 4'h3;
		      end

		      4'h3: begin
			 rb_sel     <= 1'b0;
			 alu_state <= 4'h0;
			 // jump back to instruction fetch
			 state <= 4'h0;
		      end
		    endcase; // case (alu_state)
		 end
	      end
	   end // case: 4'h1
	   
           4'h2: begin
	      // write back to RAM, one clock cycle stuff
	      mem_data_out <= r0_stat;
	      rb_sel <= 0;
	      mem_sel <= 1;
	      mem_read <= 0;
	      adress_line <= {imme_high, imme_low};
	      
	      state <= 4'h0;
	      
	   end // case: 4'h2

	   4'h3: begin
	      case (load_state)
		4'h0: begin
		   // Start memory read
		   adress_line   <= {imme_high, imme_low}; // address from immediate
		   mem_sel       <= 1'b1;
		   mem_read      <= 1'b1;
		   mem_data_out  <= 8'h00;
		   r_ch          <= 1'b0;
		   f_ch          <= 1'b0;
		   rb_sel        <= 1'b0;
		   load_state    <= 4'h1;
		end
		4'h1: begin
		   // Loaded data is now on mem_data_in.
		   // Store it as immediate, then reuse ALU passthrough to write to register.
		   imme_high     <= mem_data_in;   // loaded data becomes immediate
		   imme_low      <= 8'h00;         // not used (8‑bit loads)
		   imme          <= 1'b1;          // select immediate as ALU operand A
		   sto           <= 1'b0;          // clear store flag so we go to ALU path
		   alu_out_s     <= 4'h9;          // passthrough A (ALU out = A)
		   alu_state     <= 4'h0;          // start ALU pipeline from beginning
		   state         <= 4'h1;          // jump back to DECODE
		   load_state    <= 4'h0;          // reset for next load
		end
		default: load_state <= 4'h0;
	      endcase
	   end	  
	   
	 endcase; // case (state)
      end // else: !if(rst)
   end // always @ (posedge clk)
   
endmodule // control_unit

control_unit.vcd
$version Generated by VerilatedVcd $end
$date Thu Jul  2 11:02:46 2026 $end
$timescale 1ps $end

 $scope module TOP $end
  $var wire 16 ; adress_line [15:0] $end
  $var wire  4 A alu_out [3:0] $end
  $var wire  1 5 clk $end
  $var wire  1 B f_ch $end
  $var wire  1 9 flag_stat $end
  $var wire  8 F imme_out [7:0] $end
  $var wire  1 E imme_sel $end
  $var wire  8 7 mem_data_in [7:0] $end
  $var wire  8 : mem_data_out [7:0] $end
  $var wire  1 = mem_read $end
  $var wire  1 < mem_sel $end
  $var wire  8 8 r0_stat [7:0] $end
  $var wire  3 > r1 [2:0] $end
  $var wire  3 ? r2 [2:0] $end
  $var wire  3 @ r3 [2:0] $end
  $var wire  1 C r_ch $end
  $var wire  1 D rb_sel $end
  $var wire  1 6 rst $end
  $scope module control_unit $end
   $var wire 16 ; adress_line [15:0] $end
   $var wire  4 A alu_out [3:0] $end
   $var wire  4 / alu_out_s [3:0] $end
   $var wire  4 + alu_state [3:0] $end
   $var wire  1 5 clk $end
   $var wire  1 B f_ch $end
   $var wire  1 9 flag_stat $end
   $var wire  4 $ if_state [3:0] $end
   $var wire  1 0 imme $end
   $var wire  8 3 imme_high [7:0] $end
   $var wire  8 4 imme_low [7:0] $end
   $var wire  8 F imme_out [7:0] $end
   $var wire  1 E imme_sel $end
   $var wire  1 1 jmp $end
   $var wire  4 % load_state [3:0] $end
   $var wire  8 7 mem_data_in [7:0] $end
   $var wire  8 : mem_data_out [7:0] $end
   $var wire  1 = mem_read $end
   $var wire  1 < mem_sel $end
   $var wire 16 & pc [15:0] $end
   $var wire 16 ' pc1 [15:0] $end
   $var wire 16 ( pc2 [15:0] $end
   $var wire 16 ) pc3 [15:0] $end
   $var wire 16 * pc4 [15:0] $end
   $var wire  8 8 r0_stat [7:0] $end
   $var wire  3 > r1 [2:0] $end
   $var wire  3 , r1_s [2:0] $end
   $var wire  3 ? r2 [2:0] $end
   $var wire  3 - r2_s [2:0] $end
   $var wire  3 @ r3 [2:0] $end
   $var wire  3 . r3_s [2:0] $end
   $var wire  1 C r_ch $end
   $var wire  1 D rb_sel $end
   $var wire  1 6 rst $end
   $var wire  4 # state [3:0] $end
   $var wire  1 2 sto $end
  $upscope $end
 $upscope $end
$enddefinitions $end


#0
b0000 #
b0000 $
b0000 %
b0000000000000000 &
b0000000000000001 '
b0000000000000010 (
b0000000000000011 )
b0000000000000100 *
b0000 +
b000 ,
b000 -
b000 .
b0000 /
00
01
02
b00000000 3
b00000000 4
05
16
b00000000 7
b01010101 8
19
b00000000 :
b0000000000000000 ;
0<
0=
b000 >
b000 ?
b000 @
b0000 A
0B
0C
0D
0E
b00000000 F
#10
15
#20
05
06
#30
b0001 $
15
1<
1=
#40
05
b00000001 7
#50
b0010 $
b001 ,
15
b0000000000000001 ;
#60
05
b00100001 7
#70
b0101 $
b010 -
15
b0000000000000000 ;
0<
b001 >
#80
05
b00000000 7
#90
b0001 #
b0000 $
b0000000000000100 &
b0000000000000101 '
b0000000000000110 (
b0000000000000111 )
b0000000000001000 *
15
b010 ?
#100
05
#110
b0001 +
15
0=
1D
#120
05
#130
b0010 +
15
0D
#140
05
#150
b0011 +
15
1B
1C
1D
#160
05
#170
b0000 #
b0000 +
15
0B
0C
0D
#180
05
#190
b0001 $
15
b0000000000000100 ;
1<
1=
#200
05
b00001000 7
#210
b0010 $
b000 ,
10
15
b0000000000000101 ;
#220
05
b10000000 7
#230
b0011 $
b000 -
11
15
b0000000000000110 ;
b000 >
1E
#240
05
b00000000 7
#250
b0100 $
15
b0000000000000111 ;
b000 ?
#260
05
#270
b0101 $
15
b0000000000000000 ;
0<
#280
05
#290
b0001 #
b0000 $
b0000000000001000 &
b0000000000001001 '
b0000000000001010 (
b0000000000001011 )
b0000000000001100 *
15
#300
05
#310
b0000 #
b0000000000000000 &
b0000000000000001 '
b0000000000000010 (
b0000000000000011 )
b0000000000000100 *
15
0=
#320
05
#330
b0001 $
15
1<
1=
#340
05
b00000001 7
#350
b0010 $
b001 ,
00
15
b0000000000000001 ;
#360
05
b00100001 7
#370
b0101 $
b010 -
01
15
b0000000000000000 ;
0<
b001 >
0E
#380
05
b00000000 7
#390
b0001 #
b0000 $
b0000000000000100 &
b0000000000000101 '
b0000000000000110 (
b0000000000000111 )
b0000000000001000 *
15
b010 ?
#400
05
#410
b0001 +
15
0=
1D
#420
05
#430
b0010 +
15
0D
#440
05
#450
b0011 +
15
1B
1C
1D
#460
05
#470
b0000 #
b0000 +
15
0B
0C
0D
#480
05
#490
b0001 $
15
b0000000000000100 ;
1<
1=
#500
05
b00001000 7
#510
b0010 $
b000 ,
10
15
b0000000000000101 ;
#520
05
b10000000 7
#530
b0011 $
b000 -
11
15
b0000000000000110 ;
b000 >
1E
#540
05
b00000000 7
#550
b0100 $
15
b0000000000000111 ;
b000 ?
#560
05
#570
b0101 $
15
b0000000000000000 ;
0<
#580
05
#590
b0001 #
b0000 $
b0000000000001000 &
b0000000000001001 '
b0000000000001010 (
b0000000000001011 )
b0000000000001100 *
15
#600
05
#610
b0000 #
b0000000000000000 &
b0000000000000001 '
b0000000000000010 (
b0000000000000011 )
b0000000000000100 *
15
0=
#620
05
#630
b0001 $
15
1<
1=
#640
05
b00000001 7
#650
b0010 $
b001 ,
00
15
b0000000000000001 ;
#660
05
b00100001 7
#670
b0101 $
b010 -
01
15
b0000000000000000 ;
0<
b001 >
0E
#680
05
b00000000 7
#690
b0001 #
b0000 $
b0000000000000100 &
b0000000000000101 '
b0000000000000110 (
b0000000000000111 )
b0000000000001000 *
15
b010 ?
#700
05
#710
b0001 +
15
0=
1D
#720
05
#730
b0010 +
15
0D
#740
05
#750
b0011 +
15
1B
1C
1D
#760
05
#770
b0000 #
b0000 +
15
0B
0C
0D
#780
05
#790
b0001 $
15
b0000000000000100 ;
1<
1=
#800
05
b00001000 7
#810
b0010 $
b000 ,
10
15
b0000000000000101 ;
#820
05
b10000000 7
#830
b0011 $
b000 -
11
15
b0000000000000110 ;
b000 >
1E
#840
05
b00000000 7
#850
b0100 $
15
b0000000000000111 ;
b000 ?
#860
05
#870
b0101 $
15
b0000000000000000 ;
0<
#880
05
#890
b0001 #
b0000 $
b0000000000001000 &
b0000000000001001 '
b0000000000001010 (
b0000000000001011 )
b0000000000001100 *
15
#900
05
#910
b0000 #
b0000000000000000 &
b0000000000000001 '
b0000000000000010 (
b0000000000000011 )
b0000000000000100 *
15
0=
#920
05
#930
b0001 $
15
1<
1=
#940
05
b00000001 7
#950
b0010 $
b001 ,
00
15
b0000000000000001 ;
#960
05
b00100001 7
#970
b0101 $
b010 -
01
15
b0000000000000000 ;
0<
b001 >
0E
#980
05
b00000000 7
#990
b0001 #
b0000 $
b0000000000000100 &
b0000000000000101 '
b0000000000000110 (
b0000000000000111 )
b0000000000001000 *
15
b010 ?
#1000
05
#1010
b0001 +
15
0=
1D
#1020
05
#1030
b0010 +
15
0D
#1040
05
#1050
b0011 +
15
1B
1C
1D
#1060
05
#1070
b0000 #
b0000 +
15
0B
0C
0D
#1080
05
#1090
b0001 $
15
b0000000000000100 ;
1<
1=
#1100
05
b00001000 7
#1110
b0010 $
b000 ,
10
15
b0000000000000101 ;
#1120
05
b10000000 7
#1130
b0011 $
b000 -
11
15
b0000000000000110 ;
b000 >
1E
#1140
05
b00000000 7
#1150
b0100 $
15
b0000000000000111 ;
b000 ?
#1160
05
#1170
b0101 $
15
b0000000000000000 ;
0<
#1180
05
#1190
b0001 #
b0000 $
b0000000000001000 &
b0000000000001001 '
b0000000000001010 (
b0000000000001011 )
b0000000000001100 *
15
#1200
05
#1210
b0000 #
b0000000000000000 &
b0000000000000001 '
b0000000000000010 (
b0000000000000011 )
b0000000000000100 *
15
0=
#1220
05
#1230
b0001 $
15
1<
1=
